pylovespouse/lovespouse.py
pylovespouse-0.9.0.dist-info/LICENSE
pylovespouse-0.9.0.dist-info/METADATA
pylovespouse-0.9.0.dist-info/WHEEL
pylovespouse-0.9.0.dist-info/top_level.txt
pylovespouse-0.9.0.dist-info/RECORD
