Metadata-Version: 2.1
Name: pylovespouse
Version: 0.9.0
Summary: Interaction with lovespouse devices via Bluetooth
Author: Revenant Freddy
Classifier: Programming Language :: Python :: 3
Classifier: License :: OSI Approved :: MIT License
Classifier: Operating System :: OS Independent
Requires-Python: >=3.8
License-File: LICENSE
